integration/__init__.py
integration/test_imports.py
lofar_stingray/__init__.py
lofar_stingray/_logging.py
lofar_stingray/_minio.py
lofar_stingray/_prometheus.py
lofar_stingray/_version.py
lofar_stingray/extract.py
lofar_stingray/forward.py
lofar_stingray/publish.py
lofar_stingray/writer.py
lofar_stingray/aggregator/__init__.py
lofar_stingray/aggregator/_base.py
lofar_stingray/aggregator/_bst_aggregator.py
lofar_stingray/aggregator/_collect.py
lofar_stingray/aggregator/_sst_aggregator.py
lofar_stingray/aggregator/_xst_aggregator.py
lofar_stingray/aggregator/message.py
lofar_stingray/annotator/__init__.py
lofar_stingray/annotator/_base.py
lofar_stingray/annotator/_bst_annotator.py
lofar_stingray/annotator/_sst_annotator.py
lofar_stingray/annotator/_xst_annotator.py
lofar_stingray/reader/__init__.py
lofar_stingray/reader/_s3_packet_loader.py
lofar_stingray/streams/__init__.py
lofar_stingray/streams/_create.py
lofar_stingray/streams/_file.py
lofar_stingray/streams/_s3.py
lofar_stingray/streams/_socket.py
lofar_stingray/streams/_stream.py
lofar_stingray/streams/_tcp.py
lofar_stingray/streams/_udp.py
lofar_stingray/streams/_zmq.py
lofar_stingray/utils/__init__.py
lofar_stingray/utils/_stringray_json_encoder.py
lofar_stingray/utils/argparse.py
lofar_stingray-0.0.33.dist-info/LICENSE
lofar_stingray-0.0.33.dist-info/METADATA
lofar_stingray-0.0.33.dist-info/WHEEL
lofar_stingray-0.0.33.dist-info/entry_points.txt
lofar_stingray-0.0.33.dist-info/top_level.txt
lofar_stingray-0.0.33.dist-info/RECORD
