Metadata-Version: 2.2
Name: lofar-stingray
Version: 0.0.33
Summary: LOFAR station statistics gather and dump utility, writes station statistics continuously to the local S3 based object storage.
Home-page: https://git.astron.nl/lofar2.0/stingray
License: Apache License 2.0
Classifier: Development Status :: 3 - Alpha
Classifier: Environment :: No Input/Output (Daemon)
Classifier: Intended Audience :: Developers
Classifier: Intended Audience :: Science/Research
Classifier: License :: OSI Approved :: Apache Software License
Classifier: Operating System :: OS Independent
Classifier: Programming Language :: Python
Classifier: Programming Language :: Python :: 3
Classifier: Programming Language :: Python :: 3 :: Only
Classifier: Programming Language :: Python :: 3.11
Classifier: Programming Language :: Python :: 3.12
Classifier: Topic :: Utilities
Classifier: Topic :: System :: Archiving :: Compression
Classifier: Topic :: Scientific/Engineering
Classifier: Topic :: Scientific/Engineering :: Astronomy
Requires-Python: >=3.11
License-File: LICENSE
Requires-Dist: numpy
Requires-Dist: minio~=7.1.17
Requires-Dist: lofar-station-client>=0.21
Requires-Dist: setuptools>=70.0.0
Requires-Dist: logfmter
Requires-Dist: prometheus-client
Requires-Dist: pyzmq>=24
